LICENSE
MANIFEST.in
README.rst
setup.py
s3_backups/__init__.py
s3_backups/mysql_to_s3.py
s3_backups/postgres_to_s3.py
s3_backups/redis_to_s3.py
s3_backups/tests.py
s3_backups/utils.py
s3_backups.egg-info/PKG-INFO
s3_backups.egg-info/SOURCES.txt
s3_backups.egg-info/dependency_links.txt
s3_backups.egg-info/not-zip-safe
s3_backups.egg-info/requires.txt
s3_backups.egg-info/top_level.txt
s3_backups/schedules/__init__.py
s3_backups/schedules/default.py