Metadata-Version: 1.1
Name: s3-backups
Version: 0.1.0
Summary: Backup stuff to S3
Home-page: https://github.com/epicserve/s3-backups
Author: Brent O'Connor
Author-email: epicserve@gmail.com
License: Copyright 2013 Brent O'Connor
